pydantic_databricks-0.3.0.dist-info/METADATA
pydantic_databricks-0.3.0.dist-info/WHEEL
pydantic_databricks-0.3.0.dist-info/licenses/LICENSE
pydantic_databricks/__init__.py
pydantic_databricks/constraints.py
pydantic_databricks/models.py
pydantic_databricks/templates/__init__.py
pydantic_databricks/templates/constraints.j2
pydantic_databricks/templates/create_table.j2
pydantic_databricks-0.3.0.dist-info/RECORD
