Metadata-Version: 2.1
Name: pydantic-databricks
Version: 0.3.0
Summary: Databricks helpers for Pydantic models
Author-Email: Daniel Tom <daniel.tom@xebia.com>
License: MIT
Requires-Python: >=3.9
Requires-Dist: pydantic>=2.5.2
Requires-Dist: pydantic-spark>=1.0.1
Requires-Dist: jinja2>=3.1.2
